{
  "status": 1,
  "msg": "操作成功",
  "data": {
    "aid": 9999,
    "accountName": "breeze",
    "userName": "breeze",
    "roleName": "运营商管理员",
    "token": "123abc",
    "crmReadFunctionList": [
      {
        "id": 53830,
        "name": "卡券營銷",
        "code": "0002",
        "parentCode": "ROOT",
        "sort": 3,
        "manualSort": 0,
        "url": "0002",
        "icon": "",
        "status": 1
      },
      {
        "id": 54594,
        "name": "用戶管理",
        "code": "0001",
        "parentCode": "ROOT",
        "sort": 4,
        "manualSort": 0,
        "url": "0001",
        "icon": "",
        "status": 1
      },
      {
        "id": 54839,
        "name": "報表",
        "code": "0003",
        "parentCode": "ROOT",
        "sort": 5,
        "manualSort": 0,
        "url": "0003",
        "icon": "",
        "status": 1
      },
      {
        "id": 54595,
        "name": "用戶數據",
        "code": "00010001",
        "parentCode": "0001",
        "sort": 1,
        "manualSort": 0,
        "url": "00010001",
        "icon": "{\"iconName\":\"yong-hu-shu-ju\"}",
        "status": 1
      },
      {
        "id": 54596,
        "name": "用戶列表",
        "code": "000100010002",
        "parentCode": "00010001",
        "sort": 1,
        "manualSort": 0,
        "url": "/userList",
        "icon": "",
        "status": 1
      },
      {
        "id": 54597,
        "name": "用户详情",
        "code": "0001000100020001",
        "parentCode": "000100010002",
        "sort": 1,
        "manualSort": 0,
        "url": "/userDetails",
        "icon": "{\"activeMenuPath\":\"/userList\"}",
        "status": 1
      },
      {
        "id": 53831,
        "name": "卡券管理",
        "code": "00020001",
        "parentCode": "0002",
        "sort": 1,
        "manualSort": 1,
        "url": "00020001",
        "icon": "{\"iconName\":\"ka-quan-guan-li\"}",
        "status": 1
      },
      {
        "id": 53875,
        "name": "卡券活動",
        "code": "00020002",
        "parentCode": "0002",
        "sort": 2,
        "manualSort": 4,
        "url": "00020002",
        "icon": "{\"iconName\":\"ka-quan-huo-dong\"}",
        "status": 1
      },
      {
        "id": 54620,
        "name": "實體券",
        "code": "00020003",
        "parentCode": "0002",
        "sort": 3,
        "manualSort": 3,
        "url": "00020003",
        "icon": "{\"iconName\":\"shi-ti-quan\"}",
        "status": 1
      },
      {
        "id": 54635,
        "name": "電子券",
        "code": "00020004",
        "parentCode": "0002",
        "sort": 4,
        "manualSort": 2,
        "url": "/CouponElectronic",
        "icon": "{\"iconName\":\"dian-zi-quan\"}",
        "status": 1
      },
      {
        "id": 53832,
        "name": "券模版",
        "code": "000200010001",
        "parentCode": "00020001",
        "sort": 1,
        "manualSort": 0,
        "url": "/couponListTemp",
        "icon": "",
        "status": 1
      },
      {
        "id": 53870,
        "name": "券统计",
        "code": "000200010002",
        "parentCode": "00020001",
        "sort": 2,
        "manualSort": 0,
        "url": "/couponStatistics",
        "icon": "",
        "status": 1
      },
      {
        "id": 53871,
        "name": "券发放",
        "code": "000200010003",
        "parentCode": "00020001",
        "sort": 3,
        "manualSort": 0,
        "url": "/couponDistribute",
        "icon": "",
        "status": 1
      },
      {
        "id": 53872,
        "name": "券管理",
        "code": "000200010004",
        "parentCode": "00020001",
        "sort": 4,
        "manualSort": 2,
        "url": "/couponManagement",
        "icon": "",
        "status": 1
      },
      {
        "id": 54646,
        "name": "券領取",
        "code": "000200010005",
        "parentCode": "00020001",
        "sort": 5,
        "manualSort": 1,
        "url": "/getCouponActivity",
        "icon": "",
        "status": 1
      },
      {
        "id": 53873,
        "name": "创建券模版",
        "code": "0002000100010002",
        "parentCode": "000200010001",
        "sort": 1,
        "manualSort": 0,
        "url": "/couponDetail",
        "icon": "{\"activeMenuPath\":\"/couponListTemp\"}",
        "status": 1
      },
      {
        "id": 53891,
        "name": "模版详情",
        "code": "0002000100010003",
        "parentCode": "000200010001",
        "sort": 2,
        "manualSort": 0,
        "url": "/creatCouponTemp",
        "icon": "{\"activeMenuPath\":\"/couponListTemp\"}",
        "status": 1
      },
      {
        "id": 53874,
        "name": "发放详情",
        "code": "0002000100030001",
        "parentCode": "000200010003",
        "sort": 1,
        "manualSort": 0,
        "url": "/couponDistributeDetail",
        "icon": "{\"activeMenuPath\":\"/couponDistribute\"}",
        "status": 1
      },
      {
        "id": 53890,
        "name": "券詳情",
        "code": "0002000100040001",
        "parentCode": "000200010004",
        "sort": 1,
        "manualSort": 0,
        "url": "/couponManagementDetail",
        "icon": "{\"activeMenuPath\":\"/couponManagement\"}",
        "status": 1
      },
      {
        "id": 54647,
        "name": "創建券",
        "code": "0002000100050001",
        "parentCode": "000200010005",
        "sort": 1,
        "manualSort": 0,
        "url": "/getCouponActivity/detailForm",
        "icon": "{\"activeMenuPath\":\"/getCouponActivity\"}",
        "status": 1
      },
      {
        "id": 54648,
        "name": "領取詳情",
        "code": "0002000100050002",
        "parentCode": "000200010005",
        "sort": 2,
        "manualSort": 0,
        "url": "/getCouponActivity/detailRead",
        "icon": "{\"activeMenuPath\":\"/getCouponActivity\"}",
        "status": 1
      },
      {
        "id": 53876,
        "name": "兌換活動",
        "code": "000200020001",
        "parentCode": "00020002",
        "sort": 1,
        "manualSort": 0,
        "url": "/couponExchangeActivity",
        "icon": "",
        "status": 1
      },
      {
        "id": 54628,
        "name": "售賣活動",
        "code": "000200020002",
        "parentCode": "00020002",
        "sort": 2,
        "manualSort": 0,
        "url": "/CouponPromotion",
        "icon": "",
        "status": 1
      },
      {
        "id": 54629,
        "name": "迎新活動",
        "code": "000200020003",
        "parentCode": "00020002",
        "sort": 3,
        "manualSort": 0,
        "url": "/getCouponNewUser",
        "icon": "",
        "status": 1
      },
      {
        "id": 53877,
        "name": "創建兌換活動",
        "code": "0002000200010001",
        "parentCode": "000200020001",
        "sort": 1,
        "manualSort": 0,
        "url": "/couponExchangeActivityForm",
        "icon": "{\"activeMenuPath\":\"/couponExchangeActivity\"}",
        "status": 1
      },
      {
        "id": 53878,
        "name": "兑换活动详情",
        "code": "0002000200010002",
        "parentCode": "000200020001",
        "sort": 2,
        "manualSort": 0,
        "url": "/couponExchangeActivityDetails",
        "icon": "{\"activeMenuPath\":\"/couponExchangeActivity\"}",
        "status": 1
      },
      {
        "id": 54632,
        "name": "創建活动",
        "code": "0002000200020001",
        "parentCode": "000200020002",
        "sort": 1,
        "manualSort": 0,
        "url": "/CouponPromotion/CouponPromotionForm",
        "icon": "{\"activeMenuPath\":\"/CouponPromotion\"}",
        "status": 1
      },
      {
        "id": 54633,
        "name": "活動詳情",
        "code": "0002000200020002",
        "parentCode": "000200020002",
        "sort": 2,
        "manualSort": 0,
        "url": "/CouponPromotion/CouponPromotionDetails",
        "icon": "{\"activeMenuPath\":\"/CouponPromotion\"}",
        "status": 1
      },
      {
        "id": 54634,
        "name": "創建活動",
        "code": "0002000200030001",
        "parentCode": "000200020003",
        "sort": 1,
        "manualSort": 0,
        "url": "/getCouponNewUser/detailForm",
        "icon": "{\"activeMenuPath\":\"/getCouponNewUser\"}",
        "status": 1
      },
      {
        "id": 54642,
        "name": "活動詳情",
        "code": "0002000200030002",
        "parentCode": "000200020003",
        "sort": 2,
        "manualSort": 0,
        "url": "/getCouponNewUser/detailRead",
        "icon": "{\"activeMenuPath\":\"/getCouponNewUser\"}",
        "status": 1
      },
      {
        "id": 54621,
        "name": "實體卡券",
        "code": "000200030001",
        "parentCode": "00020003",
        "sort": 1,
        "manualSort": 0,
        "url": "/CouponPhysical",
        "icon": "",
        "status": 1
      },
      {
        "id": 54626,
        "name": "實體券碼",
        "code": "000200030002",
        "parentCode": "00020003",
        "sort": 2,
        "manualSort": 0,
        "url": "/CouponCodeManagement",
        "icon": "",
        "status": 1
      },
      {
        "id": 54668,
        "name": "券碼轉移",
        "code": "000200030003",
        "parentCode": "00020003",
        "sort": 3,
        "manualSort": 0,
        "url": "/CouponCodeTransfer",
        "icon": "",
        "status": 1
      },
      {
        "id": 54622,
        "name": "創建實體卡券",
        "code": "0002000300010001",
        "parentCode": "000200030001",
        "sort": 1,
        "manualSort": 0,
        "url": "/CouponPhysical/CouponPhysicalForm",
        "icon": "{\"activeMenuPath\":\"/CouponPhysical\"}",
        "status": 1
      },
      {
        "id": 54623,
        "name": "實體卡券詳情",
        "code": "0002000300010002",
        "parentCode": "000200030001",
        "sort": 2,
        "manualSort": 0,
        "url": "/CouponPhysical/CouponPhysicalDetails",
        "icon": "{\"activeMenuPath\":\"/CouponPhysical\"}",
        "status": 1
      },
      {
        "id": 54624,
        "name": "創建批次",
        "code": "0002000300010003",
        "parentCode": "000200030001",
        "sort": 3,
        "manualSort": 0,
        "url": "/CouponPhysical/CouponCodeBatchForm",
        "icon": "{\"activeMenuPath\":\"/CouponPhysical\"}",
        "status": 1
      },
      {
        "id": 54625,
        "name": "創建發行",
        "code": "0002000300010004",
        "parentCode": "000200030001",
        "sort": 4,
        "manualSort": 0,
        "url": "/CouponPhysical/CouponCodeReleaseForm",
        "icon": "{\"activeMenuPath\":\"/CouponPhysical\"}",
        "status": 1
      },
      {
        "id": 54627,
        "name": "券碼詳情",
        "code": "0002000300020001",
        "parentCode": "000200030002",
        "sort": 1,
        "manualSort": 0,
        "url": "/CouponCodeManagement/CouponCodeManagementDetails",
        "icon": "{\"activeMenuPath\":\"/CouponCodeManagement\"}",
        "status": 1
      },
      {
        "id": 54669,
        "name": "記錄詳情",
        "code": "0002000300030001",
        "parentCode": "000200030003",
        "sort": 1,
        "manualSort": 0,
        "url": "/CouponCodeTransfer/CouponCodeTransferDetails",
        "icon": "{\"activeMenuPath\":\"/CouponCodeTransfer\"}",
        "status": 1
      },
      {
        "id": 54636,
        "name": "創建電子券",
        "code": "000200040001",
        "parentCode": "00020004",
        "sort": 1,
        "manualSort": 0,
        "url": "/CouponElectronic/CouponElectronicForm",
        "icon": "{\"activeMenuPath\":\"/CouponElectronic\"}",
        "status": 1
      },
      {
        "id": 54637,
        "name": "電子券詳情",
        "code": "000200040002",
        "parentCode": "00020004",
        "sort": 2,
        "manualSort": 0,
        "url": "/CouponElectronic/CouponElectronicDetails",
        "icon": "{\"activeMenuPath\":\"/CouponElectronic\"}",
        "status": 1
      },
      {
        "id": 54840,
        "name": "財務報表",
        "code": "00030001",
        "parentCode": "0003",
        "sort": 1,
        "manualSort": 0,
        "url": "/financialReport",
        "icon": "",
        "status": 1
      },
      {
        "id": 54858,
        "name": "運營明細報表",
        "code": "00030002",
        "parentCode": "0003",
        "sort": 2,
        "manualSort": 0,
        "url": "/operationDetailReport",
        "icon": "",
        "status": 1
      }
    ],
    "coms8ReadFunctionList": [
      {
        "id": 53756,
        "name": "經營表現",
        "code": "0001",
        "parentCode": "ROOT",
        "sort": 1,
        "manualSort": 0,
        "url": "0001",
        "icon": "",
        "status": 1
      },
      {
        "id": 53776,
        "name": "業務管理",
        "code": "0002",
        "parentCode": "ROOT",
        "sort": 2,
        "manualSort": 0,
        "url": "0002",
        "icon": "",
        "status": 1
      },
      {
        "id": 53796,
        "name": "應用管理",
        "code": "0003",
        "parentCode": "ROOT",
        "sort": 3,
        "manualSort": 0,
        "url": "0003",
        "icon": "{\"showAllBrands\": false}",
        "status": 1
      },
      {
        "id": 53808,
        "name": "數據報表",
        "code": "0004",
        "parentCode": "ROOT",
        "sort": 4,
        "manualSort": 0,
        "url": "0004",
        "icon": "",
        "status": 1
      },
      {
        "id": 53823,
        "name": "导航栏功能",
        "code": "0099",
        "parentCode": "ROOT",
        "sort": 5,
        "manualSort": 0,
        "url": "0099",
        "icon": "{\"hiddenMenu\":true}",
        "status": 1
      },
      {
        "id": 53757,
        "name": "概覽",
        "code": "00010001",
        "parentCode": "0001",
        "sort": 1,
        "manualSort": 0,
        "url": "/index/welcome",
        "icon": "{\"iconName\":\"gai-su\"}",
        "status": 1
      },
      {
        "id": 53759,
        "name": "訂單",
        "code": "00010002",
        "parentCode": "0001",
        "sort": 2,
        "manualSort": 0,
        "url": "00010002",
        "icon": "{\"iconName\":\"ding-dan\"}",
        "status": 1
      },
      {
        "id": 53768,
        "name": "監控",
        "code": "00010003",
        "parentCode": "0001",
        "sort": 3,
        "manualSort": 0,
        "url": "00010003",
        "icon": "{\"iconName\":\"jian-kong\"}",
        "status": 1
      },
      {
        "id": 53760,
        "name": "訂單管理",
        "code": "000100020001",
        "parentCode": "00010002",
        "sort": 1,
        "manualSort": 0,
        "url": "/index/order/orderList",
        "icon": "",
        "status": 1
      },
      {
        "id": 53761,
        "name": "訂單退款",
        "code": "000100020002",
        "parentCode": "00010002",
        "sort": 2,
        "manualSort": 0,
        "url": "000100020002",
        "icon": "{\"showAllBrands\": false}",
        "status": 1
      },
      {
        "id": 53764,
        "name": "關注訂單",
        "code": "000100020003",
        "parentCode": "00010002",
        "sort": 3,
        "manualSort": 0,
        "url": "000100020003",
        "icon": "{\"showAllBrands\": false}",
        "status": 1
      },
      {
        "id": 54652,
        "name": "卡券訂單",
        "code": "000100020004",
        "parentCode": "00010002",
        "sort": 4,
        "manualSort": 0,
        "url": "/CouponOrder",
        "icon": "{\"routeBase\": \"/crm-v8\"}",
        "status": 1
      },
      {
        "id": 53887,
        "name": "訂單詳情",
        "code": "0001000200010001",
        "parentCode": "000100020001",
        "sort": 1,
        "manualSort": 0,
        "url": "/index/order/orderDetail",
        "icon": "{\"activeMenuPath\":\"/index/order/orderList\"}",
        "status": 1
      },
      {
        "id": 53762,
        "name": "退款審核",
        "code": "0001000200020001",
        "parentCode": "000100020002",
        "sort": 1,
        "manualSort": 0,
        "url": "index/finance/thirdRefund",
        "icon": "",
        "status": 1
      },
      {
        "id": 53763,
        "name": "退款記錄",
        "code": "0001000200020002",
        "parentCode": "000100020002",
        "sort": 2,
        "manualSort": 0,
        "url": "/index/finance/selfRefund",
        "icon": "",
        "status": 1
      },
      {
        "id": 53765,
        "name": "攔截訂單",
        "code": "0001000200030001",
        "parentCode": "000100020003",
        "sort": 1,
        "manualSort": 0,
        "url": "/index/order/interceptOrder",
        "icon": "",
        "status": 1
      },
      {
        "id": 53766,
        "name": "配送訂單",
        "code": "0001000200030002",
        "parentCode": "000100020003",
        "sort": 2,
        "manualSort": 0,
        "url": "/index/order/deliveryOrder",
        "icon": "",
        "status": 1
      },
      {
        "id": 53767,
        "name": "超額訂單",
        "code": "0001000200030003",
        "parentCode": "000100020003",
        "sort": 3,
        "manualSort": 0,
        "url": "/index/order/bigOrder",
        "icon": "",
        "status": 1
      },
      {
        "id": 54672,
        "name": "訂單詳情",
        "code": "0001000200040001",
        "parentCode": "000100020004",
        "sort": 1,
        "manualSort": 0,
        "url": "/CouponOrder/CouponOrderDetail",
        "icon": "{\"routeBase\": \"/crm-v8\",\"activeMenuPath\":\"/CouponOrder\"}",
        "status": 1
      },
      {
        "id": 53769,
        "name": "監控看板",
        "code": "000100030001",
        "parentCode": "00010003",
        "sort": 1,
        "manualSort": 0,
        "url": "/index/monitor",
        "icon": "",
        "status": 1
      },
      {
        "id": 53770,
        "name": "監控異常",
        "code": "000100030002",
        "parentCode": "00010003",
        "sort": 2,
        "manualSort": 0,
        "url": "000100030002",
        "icon": "{\"showAllBrands\": false}",
        "status": 1
      },
      {
        "id": 53771,
        "name": "監控通知",
        "code": "000100030003",
        "parentCode": "00010003",
        "sort": 3,
        "manualSort": 0,
        "url": "/index/monitor/messageNotification",
        "icon": "",
        "status": 1
      },
      {
        "id": 53772,
        "name": "推單失敗",
        "code": "0001000300020001",
        "parentCode": "000100030002",
        "sort": 1,
        "manualSort": 0,
        "url": "/index/monitor/pushFailed",
        "icon": "",
        "status": 1
      },
      {
        "id": 53773,
        "name": "超時訂單",
        "code": "0001000300020002",
        "parentCode": "000100030002",
        "sort": 2,
        "manualSort": 0,
        "url": "/index/monitor/overtime",
        "icon": "",
        "status": 1
      },
      {
        "id": 53774,
        "name": "配送異常",
        "code": "0001000300020003",
        "parentCode": "000100030002",
        "sort": 3,
        "manualSort": 0,
        "url": "/index/monitor/dmsError",
        "icon": "",
        "status": 1
      },
      {
        "id": 53775,
        "name": "催單投訴",
        "code": "0001000300020004",
        "parentCode": "000100030002",
        "sort": 4,
        "manualSort": 0,
        "url": "/index/monitor/callOrder",
        "icon": "",
        "status": 1
      },
      {
        "id": 53777,
        "name": "餐牌",
        "code": "00020001",
        "parentCode": "0002",
        "sort": 1,
        "manualSort": 0,
        "url": "00020001",
        "icon": "{\"iconName\":\"can-pai\",\"showAllBrands\": false}",
        "status": 1
      },
      {
        "id": 53778,
        "name": "組織",
        "code": "00020002",
        "parentCode": "0002",
        "sort": 2,
        "manualSort": 0,
        "url": "00020002",
        "icon": "{\"iconName\":\"zu-zhi\"}",
        "status": 1
      },
      {
        "id": 53779,
        "name": "配送",
        "code": "00020003",
        "parentCode": "0002",
        "sort": 3,
        "manualSort": 0,
        "url": "/index/thirdparty/dms",
        "icon": "{\"iconName\":\"pei-song\",\"showAllBrands\": false}",
        "status": 1
      },
      {
        "id": 53780,
        "name": "經營設定",
        "code": "00020004",
        "parentCode": "0002",
        "sort": 4,
        "manualSort": 0,
        "url": "00020004",
        "icon": "{\"iconName\":\"gong-zhuo-tai\"}",
        "status": 1
      },
      {
        "id": 53781,
        "name": "餐牌管理",
        "code": "000200010001",
        "parentCode": "00020001",
        "sort": 1,
        "manualSort": 0,
        "url": "/index/datainput/menu",
        "icon": "",
        "status": 1
      },
      {
        "id": 53782,
        "name": "餐品管理",
        "code": "000200010002",
        "parentCode": "00020001",
        "sort": 2,
        "manualSort": 0,
        "url": "/index/datainput/products",
        "icon": "",
        "status": 1
      },
      {
        "id": 53783,
        "name": "餐品設置",
        "code": "000200010003",
        "parentCode": "00020001",
        "sort": 3,
        "manualSort": 0,
        "url": "000200010003",
        "icon": "",
        "status": 1
      },
      {
        "id": 53838,
        "name": "推荐餐品分类",
        "code": "0002000100010001",
        "parentCode": "000200010001",
        "sort": 1,
        "manualSort": 0,
        "url": "/index/datainput/menu/recommendMenu",
        "icon": "{\"activeMenuPath\":\"/index/datainput/menu\"}",
        "status": 1
      },
      {
        "id": 53884,
        "name": "餐单编辑",
        "code": "0002000100010002",
        "parentCode": "000200010001",
        "sort": 2,
        "manualSort": 0,
        "url": "/index/datainput/menu/edit/:menu_id",
        "icon": "{\"activeMenuPath\":\"/index/datainput/menu\"}",
        "status": 1
      },
      {
        "id": 53888,
        "name": "编辑推荐配置",
        "code": "0002000100010003",
        "parentCode": "000200010001",
        "sort": 3,
        "manualSort": 0,
        "url": "/index/datainput/menu/recommendMenu/recommendMenuAction",
        "icon": "{\"activeMenuPath\":\"/index/datainput/menu\"}",
        "status": 1
      },
      {
        "id": 53839,
        "name": "创建餐品",
        "code": "0002000100020001",
        "parentCode": "000200010002",
        "sort": 1,
        "manualSort": 0,
        "url": "/index/datainput/products/product/:productId",
        "icon": "{\"activeMenuPath\":\"/index/datainput/products\"}",
        "status": 1
      },
      {
        "id": 53840,
        "name": "模板管理",
        "code": "0002000100020002",
        "parentCode": "000200010002",
        "sort": 2,
        "manualSort": 0,
        "url": "/index/datainput/products/requirement/:brand_id",
        "icon": "{\"activeMenuPath\":\"/index/datainput/products\"}",
        "status": 1
      },
      {
        "id": 53841,
        "name": "餐品/特殊要求上下架",
        "code": "0002000100020003",
        "parentCode": "000200010002",
        "sort": 3,
        "manualSort": 0,
        "url": "/index/datainput/products/shelfStatus",
        "icon": "{\"activeMenuPath\":\"/index/datainput/products\"}",
        "status": 1
      },
      {
        "id": 53842,
        "name": "共用加料上下架",
        "code": "0002000100020004",
        "parentCode": "000200010002",
        "sort": 4,
        "manualSort": 0,
        "url": "/index/datainput/products/publicChargingShelfStatus",
        "icon": "{\"activeMenuPath\":\"/index/datainput/products\"}",
        "status": 1
      },
      {
        "id": 53843,
        "name": "特殊要求模板上下架",
        "code": "0002000100020005",
        "parentCode": "000200010002",
        "sort": 5,
        "manualSort": 0,
        "url": "/index/datainput/products/propertyTemplateShelfStatus",
        "icon": "{\"activeMenuPath\":\"/index/datainput/products\"}",
        "status": 1
      },
      {
        "id": 53784,
        "name": "餐品標籤",
        "code": "0002000100030001",
        "parentCode": "000200010003",
        "sort": 1,
        "manualSort": 0,
        "url": "/index/label/labelManagement",
        "icon": "",
        "status": 1
      },
      {
        "id": 53785,
        "name": "標籤設置",
        "code": "0002000100030002",
        "parentCode": "000200010003",
        "sort": 2,
        "manualSort": 0,
        "url": "/index/label/labelApplication",
        "icon": "",
        "status": 1
      },
      {
        "id": 53844,
        "name": "标签管理",
        "code": "00020001000300010001",
        "parentCode": "0002000100030001",
        "sort": 1,
        "manualSort": 0,
        "url": "/index/label/labelManagement/labelManagement/:id",
        "icon": "{\"activeMenuPath\":\"/index/label/labelManagement\"}",
        "status": 1
      },
      {
        "id": 53786,
        "name": "品牌管理",
        "code": "000200020001",
        "parentCode": "00020002",
        "sort": 1,
        "manualSort": 0,
        "url": "/BrandList",
        "icon": "{\"routeBase\": \"/crm-v8\"}",
        "status": 1
      },
      {
        "id": 53787,
        "name": "門店管理",
        "code": "000200020002",
        "parentCode": "00020002",
        "sort": 2,
        "manualSort": 0,
        "url": "/index/datainput/store",
        "icon": "",
        "status": 1
      },
      {
        "id": 53788,
        "name": "賬號管理",
        "code": "000200020003",
        "parentCode": "00020002",
        "sort": 3,
        "manualSort": 0,
        "url": "/index/system/account",
        "icon": "",
        "status": 1
      },
      {
        "id": 53789,
        "name": "角色管理",
        "code": "000200020004",
        "parentCode": "00020002",
        "sort": 4,
        "manualSort": 0,
        "url": "/index/system/role",
        "icon": "",
        "status": 1
      },
      {
        "id": 53836,
        "name": "创建品牌",
        "code": "0002000200010001",
        "parentCode": "000200020001",
        "sort": 1,
        "manualSort": 0,
        "url": "/index/datainput/brand/:brand_id",
        "icon": "{\"hiddenMenu\":true,\"activeMenuPath\":\"/BrandList\"}",
        "status": 1
      },
      {
        "id": 53845,
        "name": "账户交易管理",
        "code": "0002000200010002",
        "parentCode": "000200020001",
        "sort": 2,
        "manualSort": 0,
        "url": "/index/finance/advanceFee",
        "icon": "{\"hiddenMenu\":true}",
        "status": 1
      },
      {
        "id": 53846,
        "name": "创建门店",
        "code": "0002000200020001",
        "parentCode": "000200020002",
        "sort": 1,
        "manualSort": 0,
        "url": "/index/datainput/store/cu/:store_id",
        "icon": "{\"activeMenuPath\":\"/index/datainput/store\"}",
        "status": 1
      },
      {
        "id": 53847,
        "name": "门店配送范围展示",
        "code": "0002000200020002",
        "parentCode": "000200020002",
        "sort": 2,
        "manualSort": 0,
        "url": "/index/datainput/store/district",
        "icon": "{\"activeMenuPath\":\"/index/datainput/store\"}",
        "status": 1
      },
      {
        "id": 53848,
        "name": "门店信息校验",
        "code": "0002000200020003",
        "parentCode": "000200020002",
        "sort": 3,
        "manualSort": 0,
        "url": "/index/datainput/store/checkInfo",
        "icon": "{\"activeMenuPath\":\"/index/datainput/store\"}",
        "status": 1
      },
      {
        "id": 53849,
        "name": "库存管理",
        "code": "0002000200020004",
        "parentCode": "000200020002",
        "sort": 4,
        "manualSort": 0,
        "url": "/index/datainput/store/inventory/:store_id",
        "icon": "{\"activeMenuPath\":\"/index/datainput/store\"}",
        "status": 1
      },
      {
        "id": 53790,
        "name": "任務中心",
        "code": "000200040001",
        "parentCode": "00020004",
        "sort": 1,
        "manualSort": 0,
        "url": "/index/taskCenter",
        "icon": "",
        "status": 1
      },
      {
        "id": 54583,
        "name": "業務設定",
        "code": "000200040005",
        "parentCode": "00020004",
        "sort": 2,
        "manualSort": 0,
        "url": "/index/datainput/businessSet",
        "icon": "{\"showAllBrands\": false}",
        "status": 1
      },
      {
        "id": 54584,
        "name": "建議反饋",
        "code": "000200040002",
        "parentCode": "00020004",
        "sort": 3,
        "manualSort": 0,
        "url": "/index/message/complain",
        "icon": "{\"showAllBrands\": false}",
        "status": 1
      },
      {
        "id": 54585,
        "name": "業務通知",
        "code": "000200040003",
        "parentCode": "00020004",
        "sort": 4,
        "manualSort": 0,
        "url": "000200040003",
        "icon": "{\"showAllBrands\": false}",
        "status": 1
      },
      {
        "id": 54586,
        "name": "原因设置",
        "code": "000200040004",
        "parentCode": "00020004",
        "sort": 5,
        "manualSort": 0,
        "url": "/index/datainput/cancel",
        "icon": "{\"showAllBrands\": false}",
        "status": 1
      },
      {
        "id": 54587,
        "name": "短信通知",
        "code": "0002000400030001",
        "parentCode": "000200040003",
        "sort": 1,
        "manualSort": 0,
        "url": "/index/website/IM",
        "icon": "",
        "status": 1
      },
      {
        "id": 54588,
        "name": "郵件通知",
        "code": "0002000400030002",
        "parentCode": "000200040003",
        "sort": 2,
        "manualSort": 0,
        "url": "/index/website/email",
        "icon": "",
        "status": 1
      },
      {
        "id": 54589,
        "name": "短信通道申请",
        "code": "00020004000300010001",
        "parentCode": "0002000400030001",
        "sort": 1,
        "manualSort": 0,
        "url": "/index/website/IM/applyIm",
        "icon": "{\"activeMenuPath\":\"/index/website/IM\"}",
        "status": 1
      },
      {
        "id": 54598,
        "name": "订单配额",
        "code": "0002000400050002",
        "parentCode": "000200040005",
        "sort": 1,
        "manualSort": 0,
        "url": "/index/datainput/quota",
        "icon": "{\"activeMenuPath\":\"/index/datainput/quota\"}",
        "status": 1
      },
      {
        "id": 54599,
        "name": "假期管理",
        "code": "0002000400050001",
        "parentCode": "000200040005",
        "sort": 2,
        "manualSort": 0,
        "url": "/index/datainput/holiday",
        "icon": "{\"activeMenuPath\":\"/index/datainput/holiday\"}",
        "status": 1
      },
      {
        "id": 54799,
        "name": "餐期管理",
        "code": "0002000400050003",
        "parentCode": "000200040005",
        "sort": 3,
        "manualSort": 0,
        "url": "/Mealschedule",
        "icon": "{\"routeBase\": \"/crm-v8\",\"activeMenuPath\":\"/Mealschedule\"}",
        "status": 1
      },
      {
        "id": 54812,
        "name": "發券原因",
        "code": "0002000400050004",
        "parentCode": "000200040005",
        "sort": 3,
        "manualSort": 0,
        "url": "/CouponIssuanceReason",
        "icon": "{\"routeBase\": \"/crm-v8\",\"activeMenuPath\":true}",
        "status": 1
      },
      {
        "id": 54600,
        "name": "通用配额规则",
        "code": "00020004000500020001",
        "parentCode": "0002000400050002",
        "sort": 1,
        "manualSort": 0,
        "url": "/index/datainput/quotaDetail",
        "icon": "{\"activeMenuPath\":\"/index/datainput/quotaDetail\"}",
        "status": 1
      },
      {
        "id": 54804,
        "name": "餐期設置",
        "code": "00020004000500030001",
        "parentCode": "0002000400050003",
        "sort": 1,
        "manualSort": 0,
        "url": "/Mealschedule/detail",
        "icon": "{\"routeBase\": \"/crm-v8\",\"activeMenuPath\":\"/Mealschedule\"}",
        "status": 1
      },
      {
        "id": 53797,
        "name": "三方",
        "code": "00030001",
        "parentCode": "0003",
        "sort": 1,
        "manualSort": 0,
        "url": "00030001",
        "icon": "{\"iconName\":\"san-fang\"}",
        "status": 1
      },
      {
        "id": 53798,
        "name": "活動",
        "code": "00030002",
        "parentCode": "0003",
        "sort": 2,
        "manualSort": 0,
        "url": "/index/marketing/selfEmployed",
        "icon": "{\"iconName\":\"huo-dong\"}",
        "status": 1
      },
      {
        "id": 53799,
        "name": "客戶端",
        "code": "00030003",
        "parentCode": "0003",
        "sort": 3,
        "manualSort": 0,
        "url": "00030003",
        "icon": "{\"iconName\":\"ke-hu-duan\"}",
        "status": 1
      },
      {
        "id": 53800,
        "name": "商家端",
        "code": "00030004",
        "parentCode": "0003",
        "sort": 4,
        "manualSort": 0,
        "url": "00030004",
        "icon": "{\"iconName\":\"shang-jia-duan\"}",
        "status": 1
      },
      {
        "id": 53801,
        "name": "連接管理",
        "code": "000300010001",
        "parentCode": "00030001",
        "sort": 1,
        "manualSort": 0,
        "url": "/index/thirdparty/apply",
        "icon": "",
        "status": 1
      },
      {
        "id": 53802,
        "name": "三方同步",
        "code": "000300010002",
        "parentCode": "00030001",
        "sort": 2,
        "manualSort": 0,
        "url": "/index/thirdparty/syn",
        "icon": "",
        "status": 1
      },
      {
        "id": 53885,
        "name": "三方活动",
        "code": "000300010003",
        "parentCode": "00030001",
        "sort": 3,
        "manualSort": 0,
        "url": "/index/marketing/thirdMarketing",
        "icon": "",
        "status": 1
      },
      {
        "id": 54590,
        "name": "推送記錄",
        "code": "000300010004",
        "parentCode": "00030001",
        "sort": 4,
        "manualSort": 0,
        "url": "/index/thirdparty/posPush",
        "icon": "",
        "status": 1
      },
      {
        "id": 53833,
        "name": "第三方外卖平台对接",
        "code": "0003000100010001",
        "parentCode": "000300010001",
        "sort": 1,
        "manualSort": 0,
        "url": "/index/thirdparty/apply/docking",
        "icon": "{\"activeMenuPath\":\"/index/thirdparty/apply\"}",
        "status": 1
      },
      {
        "id": 53834,
        "name": "第三方系统对接",
        "code": "0003000100010002",
        "parentCode": "000300010001",
        "sort": 2,
        "manualSort": 0,
        "url": "/index/thirdparty/apply/pos",
        "icon": "{\"activeMenuPath\":\"/index/thirdparty/apply\"}",
        "status": 1
      },
      {
        "id": 53883,
        "name": "映射码管理",
        "code": "0003000100010003",
        "parentCode": "000300010001",
        "sort": 3,
        "manualSort": 0,
        "url": "/index/thirdparty/apply/mapping/:id",
        "icon": "{\"activeMenuPath\":\"/index/thirdparty/apply\"}",
        "status": 1
      },
      {
        "id": 53852,
        "name": "定时同步任务管理",
        "code": "0003000100020001",
        "parentCode": "000300010002",
        "sort": 1,
        "manualSort": 0,
        "url": "/index/thirdparty/channelSyncTask",
        "icon": "{\"activeMenuPath\":\"/index/thirdparty/syn\"}",
        "status": 1
      },
      {
        "id": 53853,
        "name": "历史同步记录",
        "code": "0003000100020002",
        "parentCode": "000300010002",
        "sort": 2,
        "manualSort": 0,
        "url": "/index/thirdparty/historySyncRecord",
        "icon": "{\"activeMenuPath\":\"/index/thirdparty/syn\"}",
        "status": 1
      },
      {
        "id": 53854,
        "name": "平台餐品映射",
        "code": "0003000100020003",
        "parentCode": "000300010002",
        "sort": 3,
        "manualSort": 0,
        "url": "/index/thirdparty/proMapping",
        "icon": "{\"activeMenuPath\":\"/index/thirdparty/syn\"}",
        "status": 1
      },
      {
        "id": 53855,
        "name": "商品审核结果",
        "code": "0003000100020004",
        "parentCode": "000300010002",
        "sort": 4,
        "manualSort": 0,
        "url": "/index/thirdparty/productAuditResult",
        "icon": "{\"activeMenuPath\":\"/index/thirdparty/syn\"}",
        "status": 1
      },
      {
        "id": 53856,
        "name": "历史推送记录",
        "code": "0003000100020005",
        "parentCode": "000300010002",
        "sort": 5,
        "manualSort": 0,
        "url": "/index/thirdparty/historyPosPushRecord",
        "icon": "{\"activeMenuPath\":\"/index/thirdparty/syn\"}",
        "status": 1
      },
      {
        "id": 53892,
        "name": "新增团购券",
        "code": "0003000100030001",
        "parentCode": "000300010003",
        "sort": 1,
        "manualSort": 0,
        "url": "/index/marketing/selfEmployed/meiTuan/addMtcoupon/:uid",
        "icon": "{\"activeMenuPath\":\"/index/marketing/thirdMarketing\"}",
        "status": 1
      },
      {
        "id": 53893,
        "name": "活动详情",
        "code": "0003000100030002",
        "parentCode": "000300010003",
        "sort": 2,
        "manualSort": 0,
        "url": "/index/marketing/thirdMarketing/grab/details/:id",
        "icon": "{\"activeMenuPath\":\"/index/marketing/thirdMarketing\"}",
        "status": 1
      },
      {
        "id": 53894,
        "name": "新增Grab活动",
        "code": "0003000100030003",
        "parentCode": "000300010003",
        "sort": 3,
        "manualSort": 0,
        "url": "/index/marketing/thirdMarketing/grab/create",
        "icon": "{\"activeMenuPath\":\"/index/marketing/thirdMarketing\"}",
        "status": 1
      },
      {
        "id": 53895,
        "name": "编辑Grab活动",
        "code": "0003000100030004",
        "parentCode": "000300010003",
        "sort": 4,
        "manualSort": 0,
        "url": "/index/marketing/thirdMarketing/grab/edit/:id",
        "icon": "{\"activeMenuPath\":\"/index/marketing/thirdMarketing\"}",
        "status": 1
      },
      {
        "id": 54850,
        "name": " Shopee活动",
        "code": "0003000100030005",
        "parentCode": "000300010003",
        "sort": 5,
        "manualSort": 0,
        "url": "0003000100030005",
        "icon": "{\"activeMenuPath\":\"/index/marketing/thirdMarketing\"}",
        "status": 1
      },
      {
        "id": 54854,
        "name": "创建Shopee活动",
        "code": "00030001000300050001",
        "parentCode": "0003000100030005",
        "sort": 1,
        "manualSort": 0,
        "url": "/index/marketing/thirdMarketing/shopee/create",
        "icon": "{\"activeMenuPath\":\"/index/marketing/thirdMarketing\"}",
        "status": 1
      },
      {
        "id": 54855,
        "name": "Shopee活动详情",
        "code": "00030001000300050002",
        "parentCode": "0003000100030005",
        "sort": 2,
        "manualSort": 0,
        "url": "/index/marketing/thirdMarketing/shopee/details/:id",
        "icon": "{\"activeMenuPath\":\"/index/marketing/thirdMarketing\"}",
        "status": 1
      },
      {
        "id": 55158,
        "name": "编辑shopee活动",
        "code": "00030001000300050003",
        "parentCode": "0003000100030005",
        "sort": 3,
        "manualSort": 0,
        "url": "/index/marketing/thirdMarketing/shopee/edit/:id",
        "icon": "{\"activeMenuPath\":\"/index/marketing/thirdMarketing\"}",
        "status": 1
      },
      {
        "id": 53857,
        "name": "设置门店折扣减免限额",
        "code": "000300020001",
        "parentCode": "00030002",
        "sort": 1,
        "manualSort": 0,
        "url": "/index/marketing/preLimitCreate",
        "icon": "{\"activeMenuPath\":\"/index/marketing/selfEmployed\"}",
        "status": 1
      },
      {
        "id": 53858,
        "name": "创建权益卡",
        "code": "000300020002",
        "parentCode": "00030002",
        "sort": 2,
        "manualSort": 0,
        "url": "/index/marketing/selfEmployed/benefitCard/edit/:id",
        "icon": "{\"activeMenuPath\":\"/index/marketing/selfEmployed\"}",
        "status": 1
      },
      {
        "id": 53859,
        "name": "权益卡协议配置",
        "code": "000300020003",
        "parentCode": "00030002",
        "sort": 3,
        "manualSort": 0,
        "url": "/index/marketing/selfEmployed/benefitCard/agreementConfig",
        "icon": "{\"activeMenuPath\":\"/index/marketing/selfEmployed\"}",
        "status": 1
      },
      {
        "id": 53860,
        "name": "通知配置",
        "code": "000300020004",
        "parentCode": "00030002",
        "sort": 4,
        "manualSort": 0,
        "url": "/index/marketing/selfEmployed/benefitCard/noticeConfig",
        "icon": "{\"activeMenuPath\":\"/index/marketing/selfEmployed\"}",
        "status": 1
      },
      {
        "id": 53861,
        "name": "主推卡配置",
        "code": "000300020005",
        "parentCode": "00030002",
        "sort": 5,
        "manualSort": 0,
        "url": "/index/marketing/selfEmployed/benefitCard/recommendCardList",
        "icon": "{\"activeMenuPath\":\"/index/marketing/selfEmployed\"}",
        "status": 1
      },
      {
        "id": 53804,
        "name": "應用管理",
        "code": "000300030001",
        "parentCode": "00030003",
        "sort": 1,
        "manualSort": 0,
        "url": "/index/website/config",
        "icon": "",
        "status": 1
      },
      {
        "id": 54582,
        "name": "積分商城",
        "code": "000300030002",
        "parentCode": "00030003",
        "sort": 2,
        "manualSort": 0,
        "url": "/index/marketing/integral",
        "icon": "",
        "status": 1
      },
      {
        "id": 54806,
        "name": "應用通知",
        "code": "000300030005",
        "parentCode": "00030003",
        "sort": 2,
        "manualSort": 0,
        "url": "/appNotification",
        "icon": "{\"routeBase\": \"/crm-v8\"}",
        "status": 1
      },
      {
        "id": 54815,
        "name": "版本管理",
        "code": "000300030006",
        "parentCode": "00030003",
        "sort": 2,
        "manualSort": 0,
        "url": "/applicationManagement",
        "icon": "{\"routeBase\": \"/crm-v8\"}",
        "status": 1
      },
      {
        "id": 54800,
        "name": "條款細則",
        "code": "000300030003",
        "parentCode": "00030003",
        "sort": 3,
        "manualSort": 0,
        "url": "/termsandConditions",
        "icon": "{\"routeBase\": \"/crm-v8\"}",
        "status": 1
      },
      {
        "id": 53862,
        "name": "网站的设置",
        "code": "0003000300010001",
        "parentCode": "000300030001",
        "sort": 1,
        "manualSort": 0,
        "url": "/index/website/config/web/:keyId/:siteName",
        "icon": "{\"activeMenuPath\":\"/index/website/config\"}",
        "status": 1
      },
      {
        "id": 53863,
        "name": "微信H5的设置",
        "code": "0003000300010002",
        "parentCode": "000300030001",
        "sort": 2,
        "manualSort": 0,
        "url": "/index/website/config/H5/:keyId/:siteName",
        "icon": "{\"activeMenuPath\":\"/index/website/config\"}",
        "status": 1
      },
      {
        "id": 53864,
        "name": "小程序内容编辑",
        "code": "0003000300010003",
        "parentCode": "000300030001",
        "sort": 3,
        "manualSort": 0,
        "url": "/index/website/config/WeChat/:keyId/:siteName",
        "icon": "{\"activeMenuPath\":\"/index/website/config\"}",
        "status": 1
      },
      {
        "id": 53865,
        "name": "长图页管理编辑",
        "code": "0003000300010004",
        "parentCode": "000300030001",
        "sort": 4,
        "manualSort": 0,
        "url": "/index/website/config/longGraph/:keyId/:siteName",
        "icon": "{\"activeMenuPath\":\"/index/website/config\"}",
        "status": 1
      },
      {
        "id": 53866,
        "name": "應用詳情",
        "code": "0003000300010005",
        "parentCode": "000300030001",
        "sort": 5,
        "manualSort": 0,
        "url": "/index/website/config/editor/:keyId/:siteName",
        "icon": "{\"activeMenuPath\":\"/index/website/config\"}",
        "status": 1
      },
      {
        "id": 54801,
        "name": "條款詳情",
        "code": "0003000300030001",
        "parentCode": "000300030003",
        "sort": 1,
        "manualSort": 0,
        "url": "/termsandConditions/detail",
        "icon": "{\"routeBase\":\"/crm-v8\",\"activeMenuPath\":\"/termsandConditions\"}",
        "status": 1
      },
      {
        "id": 54807,
        "name": "通知消息详情",
        "code": "0003000300050001",
        "parentCode": "000300030005",
        "sort": 1,
        "manualSort": 0,
        "url": "/appNotification/notificationDetail",
        "icon": "{\"activeMenuPath\":\"/appNotification\",\"routeBase\": \"/crm-v8\"}",
        "status": 1
      },
      {
        "id": 54808,
        "name": "动态消息详情",
        "code": "0003000300050002",
        "parentCode": "000300030005",
        "sort": 2,
        "manualSort": 0,
        "url": "/appNotification/dynamicDetail",
        "icon": "{\"activeMenuPath\":\"/appNotification\",\"routeBase\": \"/crm-v8\"}",
        "status": 1
      },
      {
        "id": 54809,
        "name": "推广消息详情",
        "code": "0003000300050003",
        "parentCode": "000300030005",
        "sort": 2,
        "manualSort": 0,
        "url": "/appNotification/promotionDetail",
        "icon": "{\"activeMenuPath\":\"/appNotification\",\"routeBase\": \"/crm-v8\"}",
        "status": 1
      },
      {
        "id": 53805,
        "name": "打印模板",
        "code": "000300040001",
        "parentCode": "00030004",
        "sort": 1,
        "manualSort": 0,
        "url": "/index/datainput/print",
        "icon": "",
        "status": 1
      },
      {
        "id": 53806,
        "name": "登錄狀態",
        "code": "000300040002",
        "parentCode": "00030004",
        "sort": 2,
        "manualSort": 0,
        "url": "/index/monitor/bstatus",
        "icon": "",
        "status": 1
      },
      {
        "id": 53807,
        "name": "Callcenter",
        "code": "000300040003",
        "parentCode": "00030004",
        "sort": 3,
        "manualSort": 0,
        "url": "/index/website/callCenter",
        "icon": "",
        "status": 1
      },
      {
        "id": 53809,
        "name": "財務",
        "code": "00040001",
        "parentCode": "0004",
        "sort": 1,
        "manualSort": 0,
        "url": "00040001",
        "icon": "{\"iconName\":\"cai-wu\"}",
        "status": 1
      },
      {
        "id": 53810,
        "name": "報表",
        "code": "00040002",
        "parentCode": "0004",
        "sort": 2,
        "manualSort": 0,
        "url": "00040002",
        "icon": "{\"iconName\":\"bao-biao\"}",
        "status": 1
      },
      {
        "id": 53811,
        "name": "FA平台對賬",
        "code": "000400010001",
        "parentCode": "00040001",
        "sort": 1,
        "manualSort": 0,
        "url": "/index/finance/reconciliation",
        "icon": "",
        "status": 1
      },
      {
        "id": 53896,
        "name": "手动对账",
        "code": "0004000100010001",
        "parentCode": "00040001",
        "sort": 2,
        "manualSort": 0,
        "url": "/index/finance/reconciliation-handle",
        "icon": "{\"activeMenuPath\":\"/index/finance/reconciliation\"}",
        "status": 1
      },
      {
        "id": 53812,
        "name": "運營明細表",
        "code": "000400020001",
        "parentCode": "00040002",
        "sort": 1,
        "manualSort": 0,
        "url": "/index/report/service",
        "icon": "",
        "status": 1
      },
      {
        "id": 53813,
        "name": "用戶分析表",
        "code": "000400020002",
        "parentCode": "00040002",
        "sort": 2,
        "manualSort": 0,
        "url": "/index/report/customer",
        "icon": "",
        "status": 1
      },
      {
        "id": 53814,
        "name": "銷售分析表",
        "code": "000400020003",
        "parentCode": "00040002",
        "sort": 3,
        "manualSort": 0,
        "url": "/index/report/sale",
        "icon": "",
        "status": 1
      },
      {
        "id": 53815,
        "name": "財務報表",
        "code": "000400020004",
        "parentCode": "00040002",
        "sort": 4,
        "manualSort": 0,
        "url": "/index/report/finance",
        "icon": "",
        "status": 1
      },
      {
        "id": 53816,
        "name": "運營分析圖",
        "code": "000400020005",
        "parentCode": "00040002",
        "sort": 5,
        "manualSort": 0,
        "url": "/index/report/serviceChart",
        "icon": "",
        "status": 1
      },
      {
        "id": 53817,
        "name": "維度報表",
        "code": "000400020006",
        "parentCode": "00040002",
        "sort": 6,
        "manualSort": 0,
        "url": "/index/report/weidChart",
        "icon": "",
        "status": 1
      },
      {
        "id": 53818,
        "name": "自定義報表",
        "code": "000400020007",
        "parentCode": "00040002",
        "sort": 7,
        "manualSort": 0,
        "url": "/index/order/customReport",
        "icon": "",
        "status": 1
      },
      {
        "id": 53824,
        "name": "更新公告",
        "code": "00990001",
        "parentCode": "0099",
        "sort": 1,
        "manualSort": 0,
        "url": "/index/message/version",
        "icon": "",
        "status": 1
      },
      {
        "id": 53825,
        "name": "操作记录",
        "code": "00990002",
        "parentCode": "0099",
        "sort": 2,
        "manualSort": 0,
        "url": "/index/system/log",
        "icon": "",
        "status": 1
      },
      {
        "id": 53826,
        "name": "个人中心",
        "code": "00990003",
        "parentCode": "0099",
        "sort": 3,
        "manualSort": 0,
        "url": "/index/system/userCenter",
        "icon": "",
        "status": 1
      }
    ]
  }
}
